MANIFEST.in
README.md
setup.py
bin/mtdiscover
bin/mttool
mtlib/__init__.py
mtlib/device.py
mtlib/discovery.py
mtlib/exceptions.py
mtlib.egg-info/PKG-INFO
mtlib.egg-info/SOURCES.txt
mtlib.egg-info/dependency_links.txt
mtlib.egg-info/requires.txt
mtlib.egg-info/top_level.txt
test/test_integration.py