Metadata-Version: 2.1
Name: mtlib
Version: 0.0.10
Summary: UNKNOWN
Home-page: https://bitbucket.org/ericwilkison/mtlib
Author: Eric Wilkison
Author-email: ericw@wilkison.com
License: MIT License
Platform: UNKNOWN
Classifier: Programming Language :: Python :: 3
Classifier: License :: OSI Approved :: MIT License
Classifier: Operating System :: OS Independent
Provides-Extra: test
